cputils/__init__.py
cputils/common.py
cputils/config.py
cputils/menu.py
cputils/samples.py
cputils/testing.py
cputils/submit/__init__.py
cputils/submit/kattis.py
cputils-0.6.0.dist-info/licenses/LICENSE.txt
cputils-0.6.0.dist-info/METADATA
cputils-0.6.0.dist-info/WHEEL
cputils-0.6.0.dist-info/entry_points.txt
cputils-0.6.0.dist-info/top_level.txt
cputils-0.6.0.dist-info/RECORD
